Workbook

Sheet Risk Register
A1: Finance Risk Assessment (ISO 31000 / COSO ERM / Basel taxonomy)
A2: Risk ID | B2: Risk category | C2: Risk subcategory | D2: Risk event / scenario | E2: Cause / driver | F2: Consequence | G2: Risk owner | H2: L | I2: I | J2: Inherent Score | K2: Inherent Level | L2: Acceptability | M2: Financial Exposure ($) | N2: Annual Prob. (%) | O2: Expected Annual Loss ($) | P2: Treatment strategy | Q2: Control / mitigation | R2: Control effectiveness (1-5) | S2: L' | T2: I' | U2: Residual Score | V2: Residual Level | W2: Residual Acceptability | X2: Key Risk Indicator / trigger | Y2: KRI vs appetite | Z2: Status
A3: FIN-001 | B3: Credit | C3: Default risk | D3: Counterparty default in loan portfolio | E3: Economic downturn raises default rates | F3: Credit losses exceed provisions | G3: CRO | H3: 3 | I3: 4 | J3: =IF(OR(H3="",I3=""),"",H3*I3) -> 12 | K3: =IF(J3="","",IF(J3>=Scales!$P$5,"Intolerable",IF(J3>=Scales!$P$6,"High",IF(J3>=Scales!$P$7,"Medium","Low")))) -> High | L3: =IF(J3="","",IF(J3>=Scales!$P$5,"Unacceptable",IF(J3>=Scales!$P$6,"Reduce (ALARP)",IF(J3>=Scales!$P$7,"Acceptable w/ review","Acceptable")))) -> Reduce (ALARP) | M3: 5000000 | N3: 0.04 | O3: =IF(OR(M3="",N3=""),"",M3*N3) -> 200000 | P3: Reduce | Q3: Tighten underwriting, collateral & single-name limits | R3: 4 | S3: 2 | T3: 3 | U3: =IF(OR(S3="",T3=""),"",S3*T3) -> 6 | V3: =IF(U3="","",IF(U3>=Scales!$P$5,"Intolerable",IF(U3>=Scales!$P$6,"High",IF(U3>=Scales!$P$7,"Medium","Low")))) -> Medium | W3: =IF(U3="","",IF(U3>=Scales!$P$5,"Unacceptable",IF(U3>=Scales!$P$6,"Reduce (ALARP)",IF(U3>=Scales!$P$7,"Acceptable w/ review","Acceptable")))) -> Acceptable w/ review | X3: NPL ratio > 3% | Y3: Within appetite | Z3: =IF(W3="","",IF(OR(W3="Unacceptable",L3="Unacceptable"),"OPEN","Monitor")) -> Monitor
A4: FIN-002 | B4: Market | C4: Interest-rate risk | D4: Rate shock erodes bond portfolio | E4: Rapid central-bank rate moves | F4: Mark-to-market loss on AFS book | G4: Head of Treasury | H4: 3 | I4: 3 | J4: =IF(OR(H4="",I4=""),"",H4*I4) -> 9 | K4: =IF(J4="","",IF(J4>=Scales!$P$5,"Intolerable",IF(J4>=Scales!$P$6,"High",IF(J4>=Scales!$P$7,"Medium","Low")))) -> Medium | L4: =IF(J4="","",IF(J4>=Scales!$P$5,"Unacceptable",IF(J4>=Scales!$P$6,"Reduce (ALARP)",IF(J4>=Scales!$P$7,"Acceptable w/ review","Acceptable")))) -> Acceptable w/ review | M4: 8000000 | N4: 0.05 | O4: =IF(OR(M4="",N4=""),"",M4*N4) -> 400000 | P4: Reduce | Q4: Duration hedging via interest-rate swaps | R4: 4 | S4: 2 | T4: 3 | U4: =IF(OR(S4="",T4=""),"",S4*T4) -> 6 | V4: =IF(U4="","",IF(U4>=Scales!$P$5,"Intolerable",IF(U4>=Scales!$P$6,"High",IF(U4>=Scales!$P$7,"Medium","Low")))) -> Medium | W4: =IF(U4="","",IF(U4>=Scales!$P$5,"Unacceptable",IF(U4>=Scales!$P$6,"Reduce (ALARP)",IF(U4>=Scales!$P$7,"Acceptable w/ review","Acceptable")))) -> Acceptable w/ review | X4: DV01 above limit | Y4: Within appetite | Z4: =IF(W4="","",IF(OR(W4="Unacceptable",L4="Unacceptable"),"OPEN","Monitor")) -> Monitor
A5: FIN-003 | B5: Liquidity | C5: Funding liquidity | D5: Funding run / deposit outflow | E5: Loss of market confidence | F5: Inability to meet obligations as due | G5: Treasurer | H5: 2 | I5: 5 | J5: =IF(OR(H5="",I5=""),"",H5*I5) -> 10 | K5: =IF(J5="","",IF(J5>=Scales!$P$5,"Intolerable",IF(J5>=Scales!$P$6,"High",IF(J5>=Scales!$P$7,"Medium","Low")))) -> High | L5: =IF(J5="","",IF(J5>=Scales!$P$5,"Unacceptable",IF(J5>=Scales!$P$6,"Reduce (ALARP)",IF(J5>=Scales!$P$7,"Acceptable w/ review","Acceptable")))) -> Reduce (ALARP) | M5: 10000000 | N5: 0.02 | O5: =IF(OR(M5="",N5=""),"",M5*N5) -> 200000 | P5: Reduce | Q5: LCR buffer + contingency funding plan | R5: 4 | S5: 2 | T5: 4 | U5: =IF(OR(S5="",T5=""),"",S5*T5) -> 8 | V5: =IF(U5="","",IF(U5>=Scales!$P$5,"Intolerable",IF(U5>=Scales!$P$6,"High",IF(U5>=Scales!$P$7,"Medium","Low")))) -> Medium | W5: =IF(U5="","",IF(U5>=Scales!$P$5,"Unacceptable",IF(U5>=Scales!$P$6,"Reduce (ALARP)",IF(U5>=Scales!$P$7,"Acceptable w/ review","Acceptable")))) -> Acceptable w/ review | X5: LCR < 110% | Y5: Breach | Z5: =IF(W5="","",IF(OR(W5="Unacceptable",L5="Unacceptable"),"OPEN","Monitor")) -> Monitor
A6: FIN-004 | B6: Compliance | C6: AML / KYC | D6: Regulatory fine for AML control failure | E6: Gaps in transaction monitoring | F6: Penalty + remediation + reputational harm | G6: CCO | H6: 2 | I6: 4 | J6: =IF(OR(H6="",I6=""),"",H6*I6) -> 8 | K6: =IF(J6="","",IF(J6>=Scales!$P$5,"Intolerable",IF(J6>=Scales!$P$6,"High",IF(J6>=Scales!$P$7,"Medium","Low")))) -> Medium | L6: =IF(J6="","",IF(J6>=Scales!$P$5,"Unacceptable",IF(J6>=Scales!$P$6,"Reduce (ALARP)",IF(J6>=Scales!$P$7,"Acceptable w/ review","Acceptable")))) -> Acceptable w/ review | M6: 3000000 | N6: 0.06 | O6: =IF(OR(M6="",N6=""),"",M6*N6) -> 180000 | P6: Reduce | Q6: Enhanced KYC + automated monitoring + audit | R6: 3 | S6: 1 | T6: 3 | U6: =IF(OR(S6="",T6=""),"",S6*T6) -> 3 | V6: =IF(U6="","",IF(U6>=Scales!$P$5,"Intolerable",IF(U6>=Scales!$P$6,"High",IF(U6>=Scales!$P$7,"Medium","Low")))) -> Low | W6: =IF(U6="","",IF(U6>=Scales!$P$5,"Unacceptable",IF(U6>=Scales!$P$6,"Reduce (ALARP)",IF(U6>=Scales!$P$7,"Acceptable w/ review","Acceptable")))) -> Acceptable | X6: SAR backlog > 30 days | Y6: Within appetite | Z6: =IF(W6="","",IF(OR(W6="Unacceptable",L6="Unacceptable"),"OPEN","Monitor")) -> Monitor
J7: =IF(OR(H7="",I7=""),"",H7*I7) | K7: =IF(J7="","",IF(J7>=Scales!$P$5,"Intolerable",IF(J7>=Scales!$P$6,"High",IF(J7>=Scales!$P$7,"Medium","Low")))) | L7: =IF(J7="","",IF(J7>=Scales!$P$5,"Unacceptable",IF(J7>=Scales!$P$6,"Reduce (ALARP)",IF(J7>=Scales!$P$7,"Acceptable w/ review","Acceptable")))) | O7: =IF(OR(M7="",N7=""),"",M7*N7) | U7: =IF(OR(S7="",T7=""),"",S7*T7) | V7: =IF(U7="","",IF(U7>=Scales!$P$5,"Intolerable",IF(U7>=Scales!$P$6,"High",IF(U7>=Scales!$P$7,"Medium","Low")))) | W7: =IF(U7="","",IF(U7>=Scales!$P$5,"Unacceptable",IF(U7>=Scales!$P$6,"Reduce (ALARP)",IF(U7>=Scales!$P$7,"Acceptable w/ review","Acceptable")))) | Z7: =IF(W7="","",IF(OR(W7="Unacceptable",L7="Unacceptable"),"OPEN","Monitor"))
J8: =IF(OR(H8="",I8=""),"",H8*I8) | K8: =IF(J8="","",IF(J8>=Scales!$P$5,"Intolerable",IF(J8>=Scales!$P$6,"High",IF(J8>=Scales!$P$7,"Medium","Low")))) | L8: =IF(J8="","",IF(J8>=Scales!$P$5,"Unacceptable",IF(J8>=Scales!$P$6,"Reduce (ALARP)",IF(J8>=Scales!$P$7,"Acceptable w/ review","Acceptable")))) | O8: =IF(OR(M8="",N8=""),"",M8*N8) | U8: =IF(OR(S8="",T8=""),"",S8*T8) | V8: =IF(U8="","",IF(U8>=Scales!$P$5,"Intolerable",IF(U8>=Scales!$P$6,"High",IF(U8>=Scales!$P$7,"Medium","Low")))) | W8: =IF(U8="","",IF(U8>=Scales!$P$5,"Unacceptable",IF(U8>=Scales!$P$6,"Reduce (ALARP)",IF(U8>=Scales!$P$7,"Acceptable w/ review","Acceptable")))) | Z8: =IF(W8="","",IF(OR(W8="Unacceptable",L8="Unacceptable"),"OPEN","Monitor"))
J9: =IF(OR(H9="",I9=""),"",H9*I9) | K9: =IF(J9="","",IF(J9>=Scales!$P$5,"Intolerable",IF(J9>=Scales!$P$6,"High",IF(J9>=Scales!$P$7,"Medium","Low")))) | L9: =IF(J9="","",IF(J9>=Scales!$P$5,"Unacceptable",IF(J9>=Scales!$P$6,"Reduce (ALARP)",IF(J9>=Scales!$P$7,"Acceptable w/ review","Acceptable")))) | O9: =IF(OR(M9="",N9=""),"",M9*N9) | U9: =IF(OR(S9="",T9=""),"",S9*T9) | V9: =IF(U9="","",IF(U9>=Scales!$P$5,"Intolerable",IF(U9>=Scales!$P$6,"High",IF(U9>=Scales!$P$7,"Medium","Low")))) | W9: =IF(U9="","",IF(U9>=Scales!$P$5,"Unacceptable",IF(U9>=Scales!$P$6,"Reduce (ALARP)",IF(U9>=Scales!$P$7,"Acceptable w/ review","Acceptable")))) | Z9: =IF(W9="","",IF(OR(W9="Unacceptable",L9="Unacceptable"),"OPEN","Monitor"))
J10: =IF(OR(H10="",I10=""),"",H10*I10) | K10: =IF(J10="","",IF(J10>=Scales!$P$5,"Intolerable",IF(J10>=Scales!$P$6,"High",IF(J10>=Scales!$P$7,"Medium","Low")))) | L10: =IF(J10="","",IF(J10>=Scales!$P$5,"Unacceptable",IF(J10>=Scales!$P$6,"Reduce (ALARP)",IF(J10>=Scales!$P$7,"Acceptable w/ review","Acceptable")))) | O10: =IF(OR(M10="",N10=""),"",M10*N10) | U10: =IF(OR(S10="",T10=""),"",S10*T10) | V10: =IF(U10="","",IF(U10>=Scales!$P$5,"Intolerable",IF(U10>=Scales!$P$6,"High",IF(U10>=Scales!$P$7,"Medium","Low")))) | W10: =IF(U10="","",IF(U10>=Scales!$P$5,"Unacceptable",IF(U10>=Scales!$P$6,"Reduce (ALARP)",IF(U10>=Scales!$P$7,"Acceptable w/ review","Acceptable")))) | Z10: =IF(W10="","",IF(OR(W10="Unacceptable",L10="Unacceptable"),"OPEN","Monitor"))
J11: =IF(OR(H11="",I11=""),"",H11*I11) | K11: =IF(J11="","",IF(J11>=Scales!$P$5,"Intolerable",IF(J11>=Scales!$P$6,"High",IF(J11>=Scales!$P$7,"Medium","Low")))) | L11: =IF(J11="","",IF(J11>=Scales!$P$5,"Unacceptable",IF(J11>=Scales!$P$6,"Reduce (ALARP)",IF(J11>=Scales!$P$7,"Acceptable w/ review","Acceptable")))) | O11: =IF(OR(M11="",N11=""),"",M11*N11) | U11: =IF(OR(S11="",T11=""),"",S11*T11) | V11: =IF(U11="","",IF(U11>=Scales!$P$5,"Intolerable",IF(U11>=Scales!$P$6,"High",IF(U11>=Scales!$P$7,"Medium","Low")))) | W11: =IF(U11="","",IF(U11>=Scales!$P$5,"Unacceptable",IF(U11>=Scales!$P$6,"Reduce (ALARP)",IF(U11>=Scales!$P$7,"Acceptable w/ review","Acceptable")))) | Z11: =IF(W11="","",IF(OR(W11="Unacceptable",L11="Unacceptable"),"OPEN","Monitor"))
J12: =IF(OR(H12="",I12=""),"",H12*I12) | K12: =IF(J12="","",IF(J12>=Scales!$P$5,"Intolerable",IF(J12>=Scales!$P$6,"High",IF(J12>=Scales!$P$7,"Medium","Low")))) | L12: =IF(J12="","",IF(J12>=Scales!$P$5,"Unacceptable",IF(J12>=Scales!$P$6,"Reduce (ALARP)",IF(J12>=Scales!$P$7,"Acceptable w/ review","Acceptable")))) | O12: =IF(OR(M12="",N12=""),"",M12*N12) | U12: =IF(OR(S12="",T12=""),"",S12*T12) | V12: =IF(U12="","",IF(U12>=Scales!$P$5,"Intolerable",IF(U12>=Scales!$P$6,"High",IF(U12>=Scales!$P$7,"Medium","Low")))) | W12: =IF(U12="","",IF(U12>=Scales!$P$5,"Unacceptable",IF(U12>=Scales!$P$6,"Reduce (ALARP)",IF(U12>=Scales!$P$7,"Acceptable w/ review","Acceptable")))) | Z12: =IF(W12="","",IF(OR(W12="Unacceptable",L12="Unacceptable"),"OPEN","Monitor"))
J13: =IF(OR(H13="",I13=""),"",H13*I13) | K13: =IF(J13="","",IF(J13>=Scales!$P$5,"Intolerable",IF(J13>=Scales!$P$6,"High",IF(J13>=Scales!$P$7,"Medium","Low")))) | L13: =IF(J13="","",IF(J13>=Scales!$P$5,"Unacceptable",IF(J13>=Scales!$P$6,"Reduce (ALARP)",IF(J13>=Scales!$P$7,"Acceptable w/ review","Acceptable")))) | O13: =IF(OR(M13="",N13=""),"",M13*N13) | U13: =IF(OR(S13="",T13=""),"",S13*T13) | V13: =IF(U13="","",IF(U13>=Scales!$P$5,"Intolerable",IF(U13>=Scales!$P$6,"High",IF(U13>=Scales!$P$7,"Medium","Low")))) | W13: =IF(U13="","",IF(U13>=Scales!$P$5,"Unacceptable",IF(U13>=Scales!$P$6,"Reduce (ALARP)",IF(U13>=Scales!$P$7,"Acceptable w/ review","Acceptable")))) | Z13: =IF(W13="","",IF(OR(W13="Unacceptable",L13="Unacceptable"),"OPEN","Monitor"))
J14: =IF(OR(H14="",I14=""),"",H14*I14) | K14: =IF(J14="","",IF(J14>=Scales!$P$5,"Intolerable",IF(J14>=Scales!$P$6,"High",IF(J14>=Scales!$P$7,"Medium","Low")))) | L14: =IF(J14="","",IF(J14>=Scales!$P$5,"Unacceptable",IF(J14>=Scales!$P$6,"Reduce (ALARP)",IF(J14>=Scales!$P$7,"Acceptable w/ review","Acceptable")))) | O14: =IF(OR(M14="",N14=""),"",M14*N14) | U14: =IF(OR(S14="",T14=""),"",S14*T14) | V14: =IF(U14="","",IF(U14>=Scales!$P$5,"Intolerable",IF(U14>=Scales!$P$6,"High",IF(U14>=Scales!$P$7,"Medium","Low")))) | W14: =IF(U14="","",IF(U14>=Scales!$P$5,"Unacceptable",IF(U14>=Scales!$P$6,"Reduce (ALARP)",IF(U14>=Scales!$P$7,"Acceptable w/ review","Acceptable")))) | Z14: =IF(W14="","",IF(OR(W14="Unacceptable",L14="Unacceptable"),"OPEN","Monitor"))
J15: =IF(OR(H15="",I15=""),"",H15*I15) | K15: =IF(J15="","",IF(J15>=Scales!$P$5,"Intolerable",IF(J15>=Scales!$P$6,"High",IF(J15>=Scales!$P$7,"Medium","Low")))) | L15: =IF(J15="","",IF(J15>=Scales!$P$5,"Unacceptable",IF(J15>=Scales!$P$6,"Reduce (ALARP)",IF(J15>=Scales!$P$7,"Acceptable w/ review","Acceptable")))) | O15: =IF(OR(M15="",N15=""),"",M15*N15) | U15: =IF(OR(S15="",T15=""),"",S15*T15) | V15: =IF(U15="","",IF(U15>=Scales!$P$5,"Intolerable",IF(U15>=Scales!$P$6,"High",IF(U15>=Scales!$P$7,"Medium","Low")))) | W15: =IF(U15="","",IF(U15>=Scales!$P$5,"Unacceptable",IF(U15>=Scales!$P$6,"Reduce (ALARP)",IF(U15>=Scales!$P$7,"Acceptable w/ review","Acceptable")))) | Z15: =IF(W15="","",IF(OR(W15="Unacceptable",L15="Unacceptable"),"OPEN","Monitor"))
J16: =IF(OR(H16="",I16=""),"",H16*I16) | K16: =IF(J16="","",IF(J16>=Scales!$P$5,"Intolerable",IF(J16>=Scales!$P$6,"High",IF(J16>=Scales!$P$7,"Medium","Low")))) | L16: =IF(J16="","",IF(J16>=Scales!$P$5,"Unacceptable",IF(J16>=Scales!$P$6,"Reduce (ALARP)",IF(J16>=Scales!$P$7,"Acceptable w/ review","Acceptable")))) | O16: =IF(OR(M16="",N16=""),"",M16*N16) | U16: =IF(OR(S16="",T16=""),"",S16*T16) | V16: =IF(U16="","",IF(U16>=Scales!$P$5,"Intolerable",IF(U16>=Scales!$P$6,"High",IF(U16>=Scales!$P$7,"Medium","Low")))) | W16: =IF(U16="","",IF(U16>=Scales!$P$5,"Unacceptable",IF(U16>=Scales!$P$6,"Reduce (ALARP)",IF(U16>=Scales!$P$7,"Acceptable w/ review","Acceptable")))) | Z16: =IF(W16="","",IF(OR(W16="Unacceptable",L16="Unacceptable"),"OPEN","Monitor"))
J17: =IF(OR(H17="",I17=""),"",H17*I17) | K17: =IF(J17="","",IF(J17>=Scales!$P$5,"Intolerable",IF(J17>=Scales!$P$6,"High",IF(J17>=Scales!$P$7,"Medium","Low")))) | L17: =IF(J17="","",IF(J17>=Scales!$P$5,"Unacceptable",IF(J17>=Scales!$P$6,"Reduce (ALARP)",IF(J17>=Scales!$P$7,"Acceptable w/ review","Acceptable")))) | O17: =IF(OR(M17="",N17=""),"",M17*N17) | U17: =IF(OR(S17="",T17=""),"",S17*T17) | V17: =IF(U17="","",IF(U17>=Scales!$P$5,"Intolerable",IF(U17>=Scales!$P$6,"High",IF(U17>=Scales!$P$7,"Medium","Low")))) | W17: =IF(U17="","",IF(U17>=Scales!$P$5,"Unacceptable",IF(U17>=Scales!$P$6,"Reduce (ALARP)",IF(U17>=Scales!$P$7,"Acceptable w/ review","Acceptable")))) | Z17: =IF(W17="","",IF(OR(W17="Unacceptable",L17="Unacceptable"),"OPEN","Monitor"))
J18: =IF(OR(H18="",I18=""),"",H18*I18) | K18: =IF(J18="","",IF(J18>=Scales!$P$5,"Intolerable",IF(J18>=Scales!$P$6,"High",IF(J18>=Scales!$P$7,"Medium","Low")))) | L18: =IF(J18="","",IF(J18>=Scales!$P$5,"Unacceptable",IF(J18>=Scales!$P$6,"Reduce (ALARP)",IF(J18>=Scales!$P$7,"Acceptable w/ review","Acceptable")))) | O18: =IF(OR(M18="",N18=""),"",M18*N18) | U18: =IF(OR(S18="",T18=""),"",S18*T18) | V18: =IF(U18="","",IF(U18>=Scales!$P$5,"Intolerable",IF(U18>=Scales!$P$6,"High",IF(U18>=Scales!$P$7,"Medium","Low")))) | W18: =IF(U18="","",IF(U18>=Scales!$P$5,"Unacceptable",IF(U18>=Scales!$P$6,"Reduce (ALARP)",IF(U18>=Scales!$P$7,"Acceptable w/ review","Acceptable")))) | Z18: =IF(W18="","",IF(OR(W18="Unacceptable",L18="Unacceptable"),"OPEN","Monitor"))
... J24: =IF(OR(H24="",I24=""),"",H24*I24) | K24: =IF(J24="","",IF(J24>=Scales!$P$5,"Intolerable",IF(J24>=Scales!$P$6,"High",IF(J24>=Scales!$P$7,"Medium","Low")))) | L24: =IF(J24="","",IF(J24>=Scales!$P$5,"Unacceptable",IF(J24>=Scales!$P$6,"Reduce (ALARP)",IF(J24>=Scales!$P$7,"Acceptable w/ review","Acceptable")))) | O24: =IF(OR(M24="",N24=""),"",M24*N24) | U24: =IF(OR(S24="",T24=""),"",S24*T24) | V24: =IF(U24="","",IF(U24>=Scales!$P$5,"Intolerable",IF(U24>=Scales!$P$6,"High",IF(U24>=Scales!$P$7,"Medium","Low")))) | W24: =IF(U24="","",IF(U24>=Scales!$P$5,"Unacceptable",IF(U24>=Scales!$P$6,"Reduce (ALARP)",IF(U24>=Scales!$P$7,"Acceptable w/ review","Acceptable")))) | Z24: =IF(W24="","",IF(OR(W24="Unacceptable",L24="Unacceptable"),"OPEN","Monitor"))

Sheet Scales
B2: Scoring Scales & Risk Acceptability
B4: LIKELIHOOD (L) | F4: ACCEPTABILITY (Risk Score = L x I, 1-25) | O4: Thresholds used by formulas (do not move):
O5: Intolerable >= | P5: 16
B6: 1 | C6: Rare | D6: < 1% | F6: 16 | G6: Intolerable | H6: Unacceptable - must reduce risk before proceeding | O6: High >= | P6: 10
B7: 2 | C7: Unlikely | D7: 1-5% | F7: 10 | G7: High | H7: Undesirable - reduce as far as possible (ALARP); justify residual | O7: Medium >= | P7: 5
B8: 3 | C8: Possible | D8: 5-25% | F8: 5 | G8: Medium | H8: Acceptable with review / documented controls
B9: 4 | C9: Likely | D9: 25-50% | F9: 1 | G9: Low | H9: Broadly acceptable - no further action required
B10: 5 | C10: Almost certain | D10: > 50%
B12: IMPACT (I) — financial severity | F12: RISK MATRIX (cell = Impa x Like)
F13: Impact\Likelihood | G13: 1 | H13: 2 | I13: 3 | J13: 4 | K13: 5
B14: 1 | C14: Insignificant | D14: < $50k; no regulatory attention | F14: 5 | G14: 5 | H14: 10 | I14: 15 | J14: 20 | K14: 25
B15: 2 | C15: Minor | D15: $50k-$500k; minor breach | F15: 4 | G15: 4 | H15: 8 | I15: 12 | J15: 16 | K15: 20
B16: 3 | C16: Moderate | D16: $500k-$5M; reportable issue | F16: 3 | G16: 3 | H16: 6 | I16: 9 | J16: 12 | K16: 15
B17: 4 | C17: Major | D17: $5M-$50M; regulatory action / restatement | F17: 2 | G17: 2 | H17: 4 | I17: 6 | J17: 8 | K17: 10
B18: 5 | C18: Severe | D18: > $50M; solvency threat / licence risk | F18: 1 | G18: 1 | H18: 2 | I18: 3 | J18: 4 | K18: 5
B20: Expected Annual Loss = Financial Exposure ($) x Annual Probability (%). See Risk Taxonomy sheet.

Sheet Risk Taxonomy
B2: Risk Taxonomy — ISO 31000 / COSO ERM / Basel
B4: L1 Category | C4: L2 Subcategory | D4: Typical driver | E4: Example KRI | F4: Typical treatment
B5: Credit | C5: Default risk | D5: Borrower deterioration / downturn | E5: NPL ratio | F5: Collateral + single-name limits
B6: Credit | C6: Concentration risk | D6: Sector or single-name exposure | E6: Single-name % of capital | F6: Diversification limits
B7: Market | C7: Interest-rate risk | D7: Rate volatility | E7: DV01 / duration gap | F7: Interest-rate swaps (hedging)
B8: Market | C8: FX risk | D8: Currency moves | E8: Open FX position | F8: FX hedges
B9: Market | C9: Equity / commodity | D9: Price volatility | E9: Value at Risk (VaR) | F9: Position limits
B10: Liquidity | C10: Funding liquidity | D10: Deposit outflow / loss of confidence | E10: LCR / NSFR | F10: Liquidity buffer + contingency funding plan
B11: Liquidity | C11: Market liquidity | D11: Asset illiquidity | E11: Days-to-liquidate / bid-ask | F11: Hold high-quality liquid assets
B12: Operational | C12: Process failure | D12: Manual error / breaks | E12: Error rate / reconciliation breaks | F12: Automation + controls
B13: Operational | C13: Fraud | D13: Internal or external fraud | E13: Fraud loss / alert volume | F13: Segregation of duties
B14: Operational | C14: Cyber / IT | D14: System compromise or outage | E14: Incident count / downtime | F14: Security & resilience controls
B15: Compliance | C15: AML / KYC | D15: Monitoring gaps | E15: SAR backlog | F15: Enhanced monitoring + KYC
... B17: Strategic | C17: Business model | D17: Market / tech shift | E17: Revenue decline vs plan | F17: Strategy review + diversification
